[
  {
    "id": "11111",
    "score": "2",
    "review": "Didn't understand this book at all. Can someone please explain it to me?",
    "isbn": "9781933372600",
    "member_id": "2"
  },
  {
    "id": "11112",
    "score": "4",
    "review": "This book taught me about Korean and Japanese history, and the story really takes a hold of you.",
    "isbn": "9781786691378",
    "member_id": "5"
  },
  {
    "id": "11113",
    "score": "4",
    "review": "I read this novel in a single sitting, couldn't put it down before it was finished. Book of the year!",
    "isbn": "9781786691378",
    "member_id": "1"
  },
  {
    "id": "11114",
    "score": "5",
    "review": "No review was written.",
    "isbn": "9780679760801",
    "member_id": "5"
  },
  {
    "id": "11115",
    "score": "3",
    "review": "Naaah, Harry Potter and the Sorcerer's Stone is better!",
    "isbn": "9780747546245",
    "member_id": "4"
  },
  {
    "id": "11116",
    "score": "5",
    "review": "This is the book that first got me reading, I really recommend all kids to read this.",
    "isbn": "9780590353427",
    "member_id": "3"
  },
  {
    "id": "11117",
    "score": "4",
    "review": "Great read! Now I want to read the rest of the Harry Potter series!",
    "isbn": "9780590353427",
    "member_id": "2"
  },
  {
    "id": "11118",
    "score": "3",
    "review": "It was okay, might need to give the other Harry Potter books a chance.",
    "isbn": "9780590353427",
    "member_id": "5"
  },
  {
    "id": "11119",
    "score": "3",
    "review": "No review was written.",
    "isbn": "9780747551003",
    "member_id": "5"
  },
  {
    "id": "22221",
    "score": "3",
    "review": "Meh, it was okay I guess.",
    "isbn": "9780747551003",
    "member_id": "1"
  }
]
